pyping_py3/__init__.py
pyping_py3/core.py
pyping_py3-0.1.0.data/scripts/pyping_py3
pyping_py3-0.1.0.dist-info/licenses/AUTHORS
pyping_py3-0.1.0.dist-info/licenses/LICENSE
pyping_py3-0.1.0.dist-info/METADATA
pyping_py3-0.1.0.dist-info/WHEEL
pyping_py3-0.1.0.dist-info/top_level.txt
pyping_py3-0.1.0.dist-info/RECORD
