Metadata-Version: 2.4
Name: pyping-py3
Version: 0.1.0
Summary: A pure python ICMP ping implementation using raw sockets
Home-page: https://github.com/jailedfish/pyping-py3/
Author: toxinu
Author-email: toxinu@gmail.com
License: The original code derived from ping.c distributed in Linux's netkit.
Keywords: ping icmp network latency
License-File: LICENSE
License-File: AUTHORS
Dynamic: author
Dynamic: author-email
Dynamic: description
Dynamic: home-page
Dynamic: keywords
Dynamic: license
Dynamic: license-file
Dynamic: summary
